{"nodes": [{"id": "workspace_backend_app_schemas_workspace_py", "label": "workspace.py", "file_type": "code", "source_file": "backend/app/schemas/workspace.py", "source_location": "L1"}, {"id": "workspace_backend_app_schemas_workspace_workspaceopenrequest", "label": "WorkspaceOpenRequest", "file_type": "code", "source_file": "backend/app/schemas/workspace.py", "source_location": "L7", "_callable": true}, {"id": "basemodel", "label": "BaseModel", "file_type": "code", "source_file": "", "source_location": "", "origin_file": "/workspace/backend/app/schemas/workspace.py"}, {"id": "workspace_backend_app_schemas_workspace_workspacesnapshot", "label": "WorkspaceSnapshot", "file_type": "code", "source_file": "backend/app/schemas/workspace.py", "source_location": "L16", "_callable": true}], "edges": [{"source": "workspace_backend_app_schemas_workspace_py", "target": "typing", "relation": "imports_from", "context": "import", "confidence": "EXTRACTED", "source_file": "backend/app/schemas/workspace.py", "source_location": "L1", "weight": 1.0}, {"source": "workspace_backend_app_schemas_workspace_py", "target": "uuid", "relation": "imports_from", "context": "import", "confidence": "EXTRACTED", "source_file": "backend/app/schemas/workspace.py", "source_location": "L2", "weight": 1.0}, {"source": "workspace_backend_app_schemas_workspace_py", "target": "pydantic", "relation": "imports_from", "context": "import", "confidence": "EXTRACTED", "source_file": "backend/app/schemas/workspace.py", "source_location": "L4", "weight": 1.0}, {"source": "workspace_backend_app_schemas_workspace_py", "target": "workspace_backend_app_schemas_workspace_workspaceopenrequest", "relation": "contains", "confidence": "EXTRACTED", "source_file": "backend/app/schemas/workspace.py", "source_location": "L7", "weight": 1.0}, {"source": "workspace_backend_app_schemas_workspace_workspaceopenrequest", "target": "basemodel", "relation": "inherits", "confidence": "EXTRACTED", "source_file": "backend/app/schemas/workspace.py", "source_location": "L7", "weight": 1.0}, {"source": "workspace_backend_app_schemas_workspace_py", "target": "workspace_backend_app_schemas_workspace_workspacesnapshot", "relation": "contains", "confidence": "EXTRACTED", "source_file": "backend/app/schemas/workspace.py", "source_location": "L16", "weight": 1.0}, {"source": "workspace_backend_app_schemas_workspace_workspacesnapshot", "target": "basemodel", "relation": "inherits", "confidence": "EXTRACTED", "source_file": "backend/app/schemas/workspace.py", "source_location": "L16", "weight": 1.0}], "raw_calls": []}